pydantic_shapely/__init__.py
pydantic_shapely/__version__.py
pydantic_shapely/annotations.py
pydantic_shapely/base.py
pydantic_shapely/geojson/__init__.py
pydantic_shapely/geojson/feature.py
pydantic_shapely/geojson/feature_collection.py
pydantic_shapely/geojson/geometry/__init__.py
pydantic_shapely/geojson/geometry/_base.py
pydantic_shapely/geojson/geometry/geometry_collection.py
pydantic_shapely/geojson/geometry/linestring.py
pydantic_shapely/geojson/geometry/multilinestring.py
pydantic_shapely/geojson/geometry/multipoint.py
pydantic_shapely/geojson/geometry/multipolygon.py
pydantic_shapely/geojson/geometry/point.py
pydantic_shapely/geojson/geometry/polygon.py
pydantic_shapely-1.0.0a5.dist-info/METADATA
pydantic_shapely-1.0.0a5.dist-info/WHEEL
pydantic_shapely-1.0.0a5.dist-info/licenses/AUTHORS.rst
pydantic_shapely-1.0.0a5.dist-info/licenses/LICENSE
pydantic_shapely-1.0.0a5.dist-info/RECORD
