Metadata-Version: 2.4
Name: pydantic-shapely
Version: 1.0.0a5
Summary: Letting two great packages work together!
License: MIT
License-File: AUTHORS.rst
License-File: LICENSE
Author: Peter van Tol
Author-email: peter.van.tol@witteveenbos.com
Requires-Python: >=3.8,<4.0
Classifier: Development Status :: 4 - Beta
Classifier: Intended Audience :: Developers
Classifier: Intended Audience :: Information Technology
Classifier: Intended Audience :: Science/Research
Classifier: License :: OSI Approved :: MIT License
Classifier: Operating System :: MacOS
Classifier: Operating System :: Microsoft :: Windows
Classifier: Operating System :: Unix
Classifier: Programming Language :: Python
Classifier: Programming Language :: Python :: 3
Classifier: Programming Language :: Python :: 3.8
Classifier: Programming Language :: Python :: 3.9
Classifier: Programming Language :: Python :: 3.10
Classifier: Programming Language :: Python :: 3.11
Classifier: Programming Language :: Python :: 3.12
Classifier: Programming Language :: Python :: 3.13
Classifier: Programming Language :: Python :: 3.14
Classifier: Programming Language :: Python :: 3 :: Only
Classifier: Topic :: Scientific/Engineering :: GIS
Classifier: Topic :: Software Development :: Libraries :: Python Modules
Requires-Dist: pydantic (>=2.5)
Requires-Dist: setuptools (>=70.1.0,<71.0.0) ; python_version >= "3.10"
Requires-Dist: shapely (>=2.0)
Requires-Dist: typing-extensions (>=4.12.2,<5.0.0) ; python_version < "3.10"
Project-URL: Repository, https://github.com/Peter-van-Tol/pydantic-shapely
